pytest_mimic/__init__.py
pytest_mimic/mimic_manager.py
pytest_mimic/plugin.py
pytest_mimic-0.2.0.dist-info/licenses/LICENSE
pytest_mimic-0.2.0.dist-info/METADATA
pytest_mimic-0.2.0.dist-info/WHEEL
pytest_mimic-0.2.0.dist-info/entry_points.txt
pytest_mimic-0.2.0.dist-info/top_level.txt
pytest_mimic-0.2.0.dist-info/RECORD
