Metadata-Version: 2.4
Name: pytest-mimic
Version: 0.2.0
Summary: Easily record function calls while testing
Author-email: Teo Cherici <teo.cherici@clockworks.co>
Maintainer-email: Teo Cherici <teo.cherici@clockworks.co>
License: 
Project-URL: Repository, https://github.com/clockworks-data/pytest-mimic
Classifier: Framework :: Pytest
Classifier: Development Status :: 4 - Beta
Classifier: Intended Audience :: Developers
Classifier: Topic :: Software Development :: Testing
Classifier: Operating System :: OS Independent
Classifier: Programming Language :: Python
Classifier: Programming Language :: Python :: 3.9
Classifier: Programming Language :: Python :: 3.10
Classifier: Programming Language :: Python :: 3.11
Classifier: Programming Language :: Python :: 3.12
Classifier: Programming Language :: Python :: 3.13
Classifier: Programming Language :: Python :: 3 :: Only
Classifier: Programming Language :: Python :: Implementation :: CPython
Classifier: Programming Language :: Python :: Implementation :: PyPy
Classifier: License :: OSI Approved :: MIT License
Requires-Python: >=3.9
License-File: LICENSE
Requires-Dist: pytest>=6.2.0
Dynamic: license-file
